raikura/__init__.py
raikura/cli.py
raikura/core/__init__.py
raikura/core/api.py
raikura/core/audit.py
raikura/core/data.py
raikura/core/explain.py
raikura/core/features.py
raikura/core/fusion.py
raikura/core/metrics.py
raikura/core/models.py
raikura/core/pipeline.py
raikura/core/preprocess.py
raikura/core/timeseries.py
raikura/core/train.py
raikura/core/tuner.py
raikura/core/utils.py
raikura-0.1.1.dist-info/licenses/LICENSE
raikura-0.1.1.dist-info/METADATA
raikura-0.1.1.dist-info/WHEEL
raikura-0.1.1.dist-info/top_level.txt
raikura-0.1.1.dist-info/RECORD
