Metadata-Version: 2.4
Name: raikura
Version: 0.1.1
Summary: The most advanced modular machine learning library in Python
Home-page: https://github.com/orgs/RaykenAI/raikura
Author: Naitik Gupta
Author-email: Naitik Gupta <hylendust@gmail.com>
License: MIT
Project-URL: Homepage, https://github.com/RaykenAI/raikura
Project-URL: Documentation, https://github.com/RaykenAI/raikura#readme
Project-URL: Source, https://github.com/RaykenAI/raikura
Requires-Python: >=3.8
License-File: LICENSE
Requires-Dist: numpy
Requires-Dist: pandas
Requires-Dist: scikit-learn
Requires-Dist: torch
Requires-Dist: transformers
Requires-Dist: joblib
Requires-Dist: shap
Requires-Dist: fastapi
Requires-Dist: uvicorn
Requires-Dist: pyyaml
Requires-Dist: matplotlib
Requires-Dist: xgboost
Requires-Dist: lightgbm
Requires-Dist: prophet
Requires-Dist: psutil
Dynamic: author
Dynamic: home-page
Dynamic: license-file
Dynamic: requires-python
